sqlalchemy_zdb/__init__.py
sqlalchemy_zdb/compiler.py
sqlalchemy_zdb/events.py
sqlalchemy_zdb/exceptions.py
sqlalchemy_zdb/operators.py
sqlalchemy_zdb/types.py
sqlalchemy_zdb/utils.py
sqlalchemy_zdb-0.1.3.dist-info/DESCRIPTION.rst
sqlalchemy_zdb-0.1.3.dist-info/METADATA
sqlalchemy_zdb-0.1.3.dist-info/RECORD
sqlalchemy_zdb-0.1.3.dist-info/WHEEL
sqlalchemy_zdb-0.1.3.dist-info/metadata.json
sqlalchemy_zdb-0.1.3.dist-info/top_level.txt
