Metadata-Version: 2.0
Name: sqlalchemy-zdb
Version: 0.1.3
Summary: SQLAlchemy support for ZomboDB
Home-page: https://github.com/skftn/sqlalchemy_zdb
Author: xxxbobrxxx, Sander Ferdinand
Author-email: xxxbobrxxx@gmail.com, sa.ferdinand@gmail.com
License: UNKNOWN
Download-URL: https://github.com/skftn/sqlalchemy_zdb/archive/master.zip
Keywords: sqlalchemy zombodb
Platform: UNKNOWN
Classifier: Development Status :: 4 - Beta
Classifier: Environment :: Web Environment
Classifier: Intended Audience :: Developers
Classifier: License :: OSI Approved :: BSD License
Classifier: Operating System :: OS Independent
Classifier: Topic :: Software Development :: Libraries :: Python Modules
Classifier: Topic :: Utilities
Classifier: Programming Language :: Python :: 3
Requires-Dist: psycopg2
Requires-Dist: sqlalchemy (>=1.1.6)
Requires-Dist: sqlalchemy-utils
